<math xmlns="http://www.w3.org/1998/Math/MathML" display="block">
  <mrow data-mjx-texclass="INNER">
    <mo data-mjx-texclass="OPEN">|</mo>
    <mtable columnspacing="1em" rowspacing="4pt">
      <mtr>
        <mtd>
          <mi>a</mi>
        </mtd>
        <mtd>
          <mi>b</mi>
        </mtd>
      </mtr>
      <mtr>
        <mtd>
          <mi>c</mi>
        </mtd>
        <mtd>
          <mi>d</mi>
        </mtd>
      </mtr>
    </mtable>
    <mo data-mjx-texclass="CLOSE">|</mo>
  </mrow>
</math>
